ensta/Authentication.py
ensta/Credentials.py
ensta/Direct.py
ensta/Guest.py
ensta/MediaResolver.py
ensta/Mobile.py
ensta/PasswordEncryption.py
ensta/SessionManager.py
ensta/Utils.py
ensta/Web.py
ensta/WebSession.py
ensta/__init__.py
ensta/containers/BaseResponseData.py
ensta/containers/DirectThread.py
ensta/containers/DirectThreadInviter.py
ensta/containers/DirectThreadLastPermanentItem.py
ensta/containers/FollowPerson.py
ensta/containers/FollowedStatus.py
ensta/containers/Inbox.py
ensta/containers/Liker.py
ensta/containers/Likers.py
ensta/containers/PhotoUpload.py
ensta/containers/Post.py
ensta/containers/PostDetail.py
ensta/containers/PostUser.py
ensta/containers/PrivateInfo.py
ensta/containers/Profile.py
ensta/containers/ProfileHost.py
ensta/containers/ReelUpload.py
ensta/containers/Shared.py
ensta/containers/UnfollowedStatus.py
ensta/containers/__init__.py
ensta/lib/Exceptions.py
ensta/lib/Searcher.py
ensta/lib/__init__.py
ensta/parser/AddedCommentParser.py
ensta/parser/AddedCommentUserParser.py
ensta/parser/BiographyLinkParser.py
ensta/parser/CaptionParser.py
ensta/parser/CarouselMediaParser.py
ensta/parser/FollowersListParser.py
ensta/parser/FollowersParser.py
ensta/parser/FollowingsListParser.py
ensta/parser/FollowingsParser.py
ensta/parser/ImageVersionsParser.py
ensta/parser/PrivateInfoParser.py
ensta/parser/ProfileParser.py
ensta/parser/UploadedPhotoParser.py
ensta/parser/UploadedSidecarParser.py
ensta/parser/__init__.py
ensta/structures/AddedComment.py
ensta/structures/AddedCommentUser.py
ensta/structures/BioLink.py
ensta/structures/Caption.py
ensta/structures/CarouselMedia.py
ensta/structures/Follower.py
ensta/structures/Followers.py
ensta/structures/Following.py
ensta/structures/Followings.py
ensta/structures/ImageVersion.py
ensta/structures/PrivateInfo.py
ensta/structures/Profile.py
ensta/structures/ReturnedBioLink.py
ensta/structures/SidecarChild.py
ensta/structures/StoryLink.py
ensta/structures/UploadedPhoto.py
ensta/structures/UploadedSidecar.py
ensta-5.2.9.dist-info/LICENSE.txt
ensta-5.2.9.dist-info/METADATA
ensta-5.2.9.dist-info/WHEEL
ensta-5.2.9.dist-info/top_level.txt
ensta-5.2.9.dist-info/RECORD
