Metadata-Version: 2.1
Name: ensta
Version: 5.2.9
Summary: 🔥 Fastest & Simplest Python Package For Instagram Automation
Home-page: https://github.com/diezo/ensta
Download-URL: https://github.com/diezo/ensta/archive/refs/tags/v5.2.9.tar.gz
Author: Deepak Soni
Author-email: sonniiii@outlook.com
License: MIT
Keywords: instagram-client,instagram,api-wrapper,instagram-scraper,instagram-api,instagram-sdk,instagram-photos,instagram-api-python,instabot,instagram-stories,instagram-bot,instapy,instagram-downloader,instagram-account,instagram-crawler,instagram-private-api,igtv,instagram-automation,reels,instagram-feed
Classifier: Development Status :: 5 - Production/Stable
Classifier: Intended Audience :: Developers
Classifier: Topic :: Software Development :: Build Tools
Classifier: License :: OSI Approved :: MIT License
Classifier: Programming Language :: Python :: 3
Classifier: Programming Language :: Python :: 3.10
Requires-Python: >=3.10
License-File: LICENSE.txt
Requires-Dist: requests
Requires-Dist: moviepy
Requires-Dist: pillow
Requires-Dist: cryptography
Requires-Dist: pyotp
Requires-Dist: ntplib
Requires-Dist: pyquery
